{
  "sectionId": "6243299",
  "districtId": "6243343",
  "areaId": "6243509",
  "players": [
    {
      "name": "Laura Albertson",
      "gender": "Female",
      "city": "Harrisonburg",
      "state": "VA",
      "rating": "3.5",
      "rating_type": "C",
      "rating_date": "12/31/2024",
      "usta_id": "lV56FSR/G8MfgohSxwjSwA=="
    },
    {
      "name": "Beth Arnold",
      "gender": "Female",
      "city": "Broadway",
      "state": "VA",
      "rating": "3.5",
      "rating_type": "C",
      "rating_date": "12/31/2024",
      "usta_id": "5JQ1rGWNZAQrelu+MtZlnA=="
    },
    {
      "name": "Lisa Baker",
      "gender": "Female",
      "city": "Verona",
      "state": "VA",
      "rating": "3.5",
      "rating_type": "C",
      "rating_date": "12/31/2024",
      "usta_id": "7ffRddrb55Kp+vWBbitUiw=="
    },
    {
      "name": "Vickie Baker",
      "gender": "Female",
      "city": "Weyers Cave",
      "state": "VA",
      "rating": "3.5",
      "rating_type": "C",
      "rating_date": "12/31/2023",
      "usta_id": "7ffRddrb55JcpfGmG6JFzg=="
    },
    {
      "name": "Patricia Dewan",
      "gender": "Female",
      "city": "Bonita Springs",
      "state": "FL",
      "rating": "3.5",
      "rating_type": "C",
      "rating_date": "12/31/2024",
      "usta_id": "Fba2ZsdcS0T8zjOE+wPlgw=="
    },
    {
      "name": "Teresa Fisher",
      "gender": "Female",
      "city": "Rockingham",
      "state": "VA",
      "rating": "3.0",
      "rating_type": "C",
      "rating_date": "12/31/2023",
      "usta_id": "cWqxUlN+Bp5Wt/DPjzkv8g=="
    },
    {
      "name": "Janet Fulton",
      "gender": "Female",
      "city": "Mount Crawford",
      "state": "VA",
      "rating": "3.5",
      "rating_type": "C",
      "rating_date": "12/31/2024",
      "usta_id": "ssh6zxIvEogpB5vhicoUcA=="
    },
    {
      "name": "Oris Griffin",
      "gender": "Female",
      "city": "Rockingham",
      "state": "VA",
      "rating": "3.0",
      "rating_type": "C",
      "rating_date": "12/31/2024",
      "usta_id": "dhhQyjIW7cKH0td3J8ZsUw=="
    },
    {
      "name": "April Keegan",
      "gender": "Female",
      "city": "Staunton",
      "state": "VA",
      "rating": "3.5",
      "rating_type": "C",
      "rating_date": "12/31/2024",
      "usta_id": "dlZ3m4LURvSKc27PlGusFg=="
    },
    {
      "name": "Elaine Mccoola",
      "gender": "Female",
      "city": "Fishersville",
      "state": "VA",
      "rating": "3.5",
      "rating_type": "S",
      "rating_date": "11/27/2024",
      "usta_id": "U7UzYQ1JWtDqzMk7Kfaj5Q=="
    },
    {
      "name": "Gayle Moore",
      "gender": "Female",
      "city": "Staunton",
      "state": "VA",
      "rating": "3.5",
      "rating_type": "C",
      "rating_date": "12/31/2024",
      "usta_id": "pziSGC7JtuYUqptB9tv7fw=="
    },
    {
      "name": "Donna Perez",
      "gender": "Female",
      "city": "Staunton",
      "state": "VA",
      "rating": "3.5",
      "rating_type": "C",
      "rating_date": "12/31/2024",
      "usta_id": "hP0XnOHs8rrZY6WSn+NNtA=="
    },
    {
      "name": "Kimberly Ridings",
      "gender": "Female",
      "city": "Staunton",
      "state": "VA",
      "rating": "4.0",
      "rating_type": "C",
      "rating_date": "12/31/2024",
      "usta_id": "1bNwlJiWbwWYXXdW5z8TeQ=="
    },
    {
      "name": "Doris Scott",
      "gender": "Female",
      "city": "Staunton",
      "state": "VA",
      "rating": "3.5",
      "rating_type": "C",
      "rating_date": "12/31/2024",
      "usta_id": "Mx3YzDMu0jbE78noNJQAFg=="
    },
    {
      "name": "Peggy Tabb",
      "gender": "Female",
      "city": "Mc Gaheysville",
      "state": "VA",
      "rating": "3.0",
      "rating_type": "C",
      "rating_date": "12/31/2024",
      "usta_id": "MjJq3m32vEOXquxdHLq7/A=="
    },
    {
      "name": "Mary Toro",
      "gender": "Female",
      "city": "NELLYSFORD",
      "state": "VA",
      "rating": "3.5",
      "rating_type": "C",
      "rating_date": "12/31/2024",
      "usta_id": "YC7hWDHkrj+E5m2vvfAQ7g=="
    },
    {
      "name": "Eileen Waterhouse",
      "gender": "Female",
      "city": "Harrisonburg",
      "state": "VA",
      "rating": "4.0",
      "rating_type": "C",
      "rating_date": "12/31/2024",
      "usta_id": "8GZyU+2vd/RTu4R5JxBZOg=="
    },
    {
      "name": "Ronda Weber",
      "gender": "Female",
      "city": "Rockingham",
      "state": "VA",
      "rating": "3.0",
      "rating_type": "S",
      "rating_date": "5/12/2025",
      "usta_id": "TSiV1eBkwEFxgrtVY3GGPw=="
    },
    {
      "name": "Shirley Webster",
      "gender": "Female",
      "city": "Verona",
      "state": "VA",
      "rating": "0.0",
      "rating_type": "None",
      "rating_date": "",
      "usta_id": "XXXgiV7mOB9KtQLYZ2k8Pw=="
    },
    {
      "name": "Mary Witt",
      "gender": "Female",
      "city": "Bridgewater",
      "state": "VA",
      "rating": "3.5",
      "rating_type": "C",
      "rating_date": "12/31/2024",
      "usta_id": "dWAHdLfggFXzOqRtUPYM0w=="
    },
    {
      "name": "Kelli Wood",
      "gender": "Female",
      "city": "STAUNTON",
      "state": "VA",
      "rating": "3.5",
      "rating_type": "C",
      "rating_date": "12/31/2024",
      "usta_id": "tEI7Idy7Mc5Mg2i4l8b/kQ=="
    }
  ]
}